antiberty_pytorch/__init__.py
antiberty_pytorch/antiberty_pytorch.py
antiberty_pytorch/data.py
antiberty_pytorch/train.py
antiberty_pytorch-0.0.1.dist-info/METADATA
antiberty_pytorch-0.0.1.dist-info/WHEEL
antiberty_pytorch-0.0.1.dist-info/top_level.txt
antiberty_pytorch-0.0.1.dist-info/RECORD
